vtoolslan/__init__.py
vtoolslan-1.1.dist-info/LICENSE.md
vtoolslan-1.1.dist-info/METADATA
vtoolslan-1.1.dist-info/WHEEL
vtoolslan-1.1.dist-info/top_level.txt
vtoolslan-1.1.dist-info/zip-safe
vtoolslan-1.1.dist-info/RECORD
