Metadata-Version: 2.1
Name: vtoolslan
Version: 1.1
Summary: A tool to change the types of different connections bettwen vms.
Home-page: https://github.com/CastellaniDavide/vtoolslan
Author: CastellaniDavide
Author-email: help@castellanidavide.it
License: GNU
Platform: linux_distibution
Requires-Python: >=3.6
Requires-Dist: tabular-log
Requires-Dist: requests
Requires-Dist: programGUI (>=1.4)
